pyhmsa/__init__.py
pyhmsa/gui/__init__.py
pyhmsa/gui/spec/__init__.py
pyhmsa/gui/spec/header.py
pyhmsa/gui/spec/condition/__init__.py
pyhmsa/gui/spec/condition/acquisition.py
pyhmsa/gui/spec/condition/calibration.py
pyhmsa/gui/spec/condition/composition.py
pyhmsa/gui/spec/condition/condition.py
pyhmsa/gui/spec/condition/detector.py
pyhmsa/gui/spec/condition/elementalid.py
pyhmsa/gui/spec/condition/instrument.py
pyhmsa/gui/spec/condition/probe.py
pyhmsa/gui/spec/condition/region.py
pyhmsa/gui/spec/condition/specimen.py
pyhmsa/gui/spec/condition/specimenposition.py
pyhmsa/gui/spec/datum/__init__.py
pyhmsa/gui/spec/datum/analysis.py
pyhmsa/gui/spec/datum/analysislist.py
pyhmsa/gui/spec/datum/datum.py
pyhmsa/gui/spec/datum/imageraster.py
pyhmsa/gui/util/__init__.py
pyhmsa/gui/util/human.py
pyhmsa/gui/util/icon.py
pyhmsa/gui/util/layout.py
pyhmsa/gui/util/messagebox.py
pyhmsa/gui/util/parameter.py
pyhmsa/gui/util/periodictable.py
pyhmsa/gui/util/registry.py
pyhmsa/gui/util/settings.py
pyhmsa/gui/util/validation.py
pyhmsa/gui/util/widget.py
pyhmsa/gui/util/mpl/__init__.py
pyhmsa/gui/util/mpl/color.py
pyhmsa/gui/util/mpl/modest_image.py
pyhmsa/gui/util/mpl/scalebar.py
pyhmsa/gui/util/mpl/toolbar.py
pyhmsa/gui/util/icons/pyhmsa.rcc
pyhmsa/gui/util/icons/tango.rcc
pyHMSA_gui-0.1.4.dist-info/zip-safe
pyHMSA_gui-0.1.4.dist-info/entry_points.txt
pyHMSA_gui-0.1.4.dist-info/top_level.txt
pyHMSA_gui-0.1.4.dist-info/METADATA
pyHMSA_gui-0.1.4.dist-info/DESCRIPTION.rst
pyHMSA_gui-0.1.4.dist-info/metadata.json
pyHMSA_gui-0.1.4.dist-info/WHEEL
pyHMSA_gui-0.1.4.dist-info/RECORD
