Metadata-Version: 2.0
Name: pyHMSA-gui
Version: 0.1.4
Summary: Graphical components to represent HMSA specification
Home-page: http://pyhmsa.readthedocs.org
Author: Philippe Pinard
Author-email: philippe.pinard@gmail.com
License: MIT
Keywords: microscopy microanalysis hmsa file format gui
Platform: UNKNOWN
Classifier: Development Status :: 4 - Beta
Classifier: Intended Audience :: Developers
Classifier: Intended Audience :: Science/Research
Classifier: Operating System :: OS Independent
Classifier: License :: OSI Approved :: MIT License
Classifier: Programming Language :: Python :: 2
Classifier: Programming Language :: Python :: 2.7
Classifier: Programming Language :: Python :: 3
Classifier: Programming Language :: Python :: 3.4
Classifier: Topic :: Scientific/Engineering :: Physics
Requires-Dist: pyHMSA
Requires-Dist: PySide
Requires-Dist: matplotlib
Requires-Dist: numpy
Requires-Dist: six
